rado/__init__.py
rado/rado.py
rado/core/__init__.py
rado/core/exceptions.py
rado/core/logger.py
rado/template/__init__.py
rado/template/conftest.py
rado/template/Result/__init__.py
rado/template/core/__init__.py
rado/template/logs/__init__.py
rado/template/preparedData/__init__.py
rado/template/test_case/__init__.py
rado/template/utilse/__init__.py
rado/utilse/__init__.py
rado/utilse/base.py
rado/utilse/sshConnection.py
Rado-0.0.2.dist-info/LICENSE
Rado-0.0.2.dist-info/METADATA
Rado-0.0.2.dist-info/WHEEL
Rado-0.0.2.dist-info/entry_points.txt
Rado-0.0.2.dist-info/top_level.txt
Rado-0.0.2.dist-info/RECORD
