Metadata-Version: 2.1
Name: Rado
Version: 0.0.2
Summary: The InterFace Test Framework based on PyTest, Request and Allure
Home-page: https://github.com/TheoTT/my_doc
Author: lit
Author-email: tt137378245@outlook.com
License: UNKNOWN
Platform: UNKNOWN
Classifier: Programming Language :: Python :: 3
Classifier: License :: OSI Approved :: MIT License
Classifier: Operating System :: OS Independent
Requires-Dist: allure-pytest (==2.6.5)
Requires-Dist: Click (==7.0)
Requires-Dist: colorama (==0.4.1)
Requires-Dist: colorlog (==4.0.2)
Requires-Dist: datatest (==0.9.6)
Requires-Dist: jsonpath (==0.81)
Requires-Dist: paramiko (==2.5.0)
Requires-Dist: xlrd (==1.2.0)
Requires-Dist: requests (==2.22.0)
Provides-Extra: rado
